mux2to1.v
module mux2to1(input [1:0] DATA_IN, input SELECT, output reg DATA_OUT);
    
	always @(*) begin
        case(SELECT)
            1'b0: DATA_OUT = DATA_IN[0];
            1'b1: DATA_OUT = DATA_IN[1];
            default: DATA_OUT = 1'b0;
        endcase
    end
	
endmodule

mux4to1.v
module mux4to1(input [3:0] DATA_IN, input [1:0] SELECT, output reg DATA_OUT);
    
	always @(*) begin
        case(SELECT)
            2'b00: DATA_OUT = DATA_IN[0];
            2'b01: DATA_OUT = DATA_IN[1];
            2'b10: DATA_OUT = DATA_IN[2];
            2'b11: DATA_OUT = DATA_IN[3];
            default: DATA_OUT = 1'b0;
        endcase
    end
	
endmodule

mux8to1.v
module mux8to1(input [7:0] DATA_IN, input [2:0] SELECT, output DATA_OUT);
    
	wire [1:0] muxout;

    mux4to1 mux1 (.DATA_IN(DATA_IN[3:0]), .SELECT(SELECT[1:0]), .DATA_OUT(muxout[0]));
    
	mux4to1 mux2 (.DATA_IN(DATA_IN[7:4]), .SELECT(SELECT[1:0]), .DATA_OUT(muxout[1]));
    
	mux2to1 mux3 (.DATA_IN(muxout), .SELECT(SELECT[2]), .DATA_OUT(DATA_OUT));
	
endmodule

mux8to1_tb.v
module mux8to1_tb();
    
	reg [7:0] data_in;
    reg [2:0] select;
    wire data_out;

    mux8to1 uut (.DATA_IN(data_in), .SELECT(select), .DATA_OUT(data_out));

    initial begin
        $dumpfile("mux8to1.vcd");
        $dumpvars;

        data_in = 8'b10101010;
        
        #10 select = 3'b000;
        #10 select = 3'b001;
        #10 select = 3'b010;
        #10 select = 3'b011;
        #10 select = 3'b100;
        #10 select = 3'b101;
        #10 select = 3'b110;
        #10 select = 3'b111;
        
        #10 $finish;
    end
	
endmodule

mux8to1.vcd
$date
	Fri Jul 26 17:07:19 2024
$end
$version
	Icarus Verilog
$end
$timescale
	1s
$end
$scope module mux8to1_tb $end
$var wire 1 ! data_out $end
$var reg 8 " data_in [7:0] $end
$var reg 3 # select [2:0] $end
$scope module uut $end
$var wire 8 $ DATA_IN [7:0] $end
$var wire 3 % SELECT [2:0] $end
$var wire 2 & muxout [1:0] $end
$var wire 1 ! DATA_OUT $end
$scope module mux1 $end
$var wire 4 ' DATA_IN [3:0] $end
$var wire 2 ( SELECT [1:0] $end
$var reg 1 ) DATA_OUT $end
$upscope $end
$scope module mux2 $end
$var wire 4 * DATA_IN [3:0] $end
$var wire 2 + SELECT [1:0] $end
$var reg 1 , DATA_OUT $end
$upscope $end
$scope module mux3 $end
$var wire 2 - DATA_IN [1:0] $end
$var wire 1 . SELECT $end
$var reg 1 ! DATA_OUT $end
$upscope $end
$upscope $end
$upscope $end
$enddefinitions $end
$comment Show the parameter values. $end
$dumpall
$end
#0
$dumpvars
x.
b0 -
0,
bx +
b1010 *
0)
bx (
b1010 '
b0 &
bx %
b10101010 $
bx #
b10101010 "
0!
$end
#10
b0 (
b0 +
0.
b0 #
b0 %
#20
1!
1)
b11 &
b11 -
1,
b1 (
b1 +
b1 #
b1 %
#30
0!
0)
b0 &
b0 -
0,
b10 (
b10 +
b10 #
b10 %
#40
1!
1)
b11 &
b11 -
1,
b11 (
b11 +
b11 #
b11 %
#50
0!
0)
b0 &
b0 -
0,
b0 (
b0 +
1.
b100 #
b100 %
#60
1!
1)
b11 &
b11 -
1,
b1 (
b1 +
b101 #
b101 %
#70
0!
0)
b0 &
b0 -
0,
b10 (
b10 +
b110 #
b110 %
#80
1!
1)
b11 &
b11 -
1,
b11 (
b11 +
b111 #
b111 %
